tap_minio_csv/__init__.py
tap_minio_csv/config.py
tap_minio_csv/conversion.py
tap_minio_csv/discover.py
tap_minio_csv/s3.py
tap_minio_csv/sync.py
tap_minio_csv-1.2.2.dist-info/LICENSE
tap_minio_csv-1.2.2.dist-info/METADATA
tap_minio_csv-1.2.2.dist-info/WHEEL
tap_minio_csv-1.2.2.dist-info/entry_points.txt
tap_minio_csv-1.2.2.dist-info/top_level.txt
tap_minio_csv-1.2.2.dist-info/RECORD
